MANIFEST.in
README.md
setup.py
PyProbe.egg-info/PKG-INFO
PyProbe.egg-info/SOURCES.txt
PyProbe.egg-info/dependency_links.txt
PyProbe.egg-info/top_level.txt
pyprobe/__init__.py
pyprobe/baseparser.py
pyprobe/ffprobeparsers.py
pyprobe/helpers.py
pyprobe/mediainfoparsers.py
pyprobe/pyprobe.py