Metadata-Version: 2.1
Name: PyProbe
Version: 0.1.1
Summary: Extract metadata from video files using ffprobe or mediainfo
Home-page: https://github.com/Protinon/PyProbe
Author: Protinon
Author-email: Protinon99@gmail.com
License: MIT
Keywords: ffprobe,mediainfo,parser,video
Platform: UNKNOWN
Classifier: Development Status :: 4 - Beta
Classifier: Natural Language :: English
Classifier: Intended Audience :: Developers
Classifier: Operating System :: OS Independent
Classifier: License :: OSI Approved :: MIT License
Classifier: Topic :: Multimedia :: Video
Classifier: Topic :: Multimedia :: Sound/Audio :: Analysis
Classifier: Programming Language :: Python :: 3 :: Only
Requires-Python: >=3
